<?xml version="1.0" encoding="utf-8"?>
<!-- EN-Revision: 43d07782b514d0c7a8487f2c74063739f302df8d	 Maintainer: sobak Status: ready -->
<sect1 xml:id="language.operators.string">
 <title>Operatory ciągów znaków</title>
 <titleabbrev>Ciąg znaków</titleabbrev>
 <simpara>
  Istnieją dwa operatory związane z typem <type>string</type>. Pierwszy
  to operator konkatenacji lub łączenia ('.'), który zwraca połączony łańcuch znaków
  ze swojego lewego i prawego argumentu. Drugi to operator konkatenacji i przypisania
  ('<literal>.=</literal>'), który dopisuje argument po prawej stronie do
  argumentu po lewej stronie. Przeczytaj rozdział <link
  linkend="language.operators.assignment">Operatory
  przypisania</link>, aby dowiedzieć się więcej.
 </simpara>

 <para>
  <informalexample>
   <programlisting role="php">
<![CDATA[
<?php
$a = "Hello ";
$b = $a . "World!"; // $b zawiera teraz "Hello World!"

$a = "Hello ";
$a .= "World!";     // $a zawiera teraz "Hello World!"
?>
]]>
   </programlisting>
  </informalexample>
 </para>

 <sect2 role="seealso">
  &reftitle.seealso;
  <para>
   <simplelist>
    <member><link linkend="language.types.string">Typ string</link></member>
    <member><link linkend="ref.strings">Funkcje ciągów znaków</link></member>
   </simplelist>
  </para>
 </sect2>
</sect1>
